{
 "id": "ro5_sv_7_b",
 "levelId": "level_rogue5_sv-7-b",
 "tags": [
  "rogue_yan"
 ],
 "category": null,
 "characterLimit": 6,
 "initialCost": 10,
 "maxCost": 99,
 "costIncreaseTime": 1.0,
 "code": "ISW-NO",
 "name_zh": "不鉴",
 "name_ja": null,
 "name_en": null,
 "description_zh": "惟余复哀。\n<@rolv.rem>胜利后获得收藏品及其他奖励</>\n<@rolv.rem>场地中有夺取后可以治疗友方单位并对敌方造成法术伤害的<\"留声机\"></>",
 "description_ja": null,
 "description_en": null,
 "addInfo_zh": null,
 "addInfo_ja": null,
 "addInfo_en": null,
 "eliteDesc_zh": null,
 "eliteDesc_ja": null,
 "eliteDesc_en": null,
 "n_mods": null,
 "elite_mods": null,
 "floors": [
  1,
  2,
  3,
  4,
  5
 ],
 "sp_terrain": null,
 "sp_enemy": {
  "normal": "1",
  "elite": null
 },
 "n_count": [
  0
 ],
 "e_count": null,
 "traps": [
  {
   "key": "trap_014_tower",
   "alias": "trap_014_tower#1",
   "pos": {
    "row": 3,
    "col": 3
   },
   "direction": "UP",
   "level": 1,
   "mainSkillLvl": 2,
   "hidden": false
  },
  {
   "key": "trap_037_airsup",
   "alias": "trap_037_airsup#1",
   "pos": {
    "row": 4,
    "col": 8
   },
   "direction": "UP",
   "level": 1,
   "mainSkillLvl": 1,
   "hidden": false
  }
 ],
 "token_cards": [],
 "enemies": [
  {
   "id": "enemy_2001_duckmi",
   "prefabKey": "enemy_2001_duckmi",
   "level": 2,
   "min_count": 0,
   "max_count": 0,
   "elite_min_count": 0,
   "elite_max_count": 0,
   "overwrittenData": null
  },
  {
   "id": "enemy_2085_skzjxd",
   "prefabKey": "enemy_2085_skzjxd",
   "level": 2,
   "min_count": 0,
   "max_count": 0,
   "elite_min_count": 0,
   "elite_max_count": 0,
   "overwrittenData": null
  },
  {
   "id": "enemy_2002_bearmi",
   "prefabKey": "enemy_2002_bearmi",
   "level": 2,
   "min_count": 0,
   "max_count": 0,
   "elite_min_count": 0,
   "elite_max_count": 0,
   "overwrittenData": null
  },
  {
   "id": "enemy_2034_sythef",
   "prefabKey": "enemy_2034_sythef",
   "level": 2,
   "min_count": 0,
   "max_count": 0,
   "elite_min_count": 0,
   "elite_max_count": 0,
   "overwrittenData": null
  },
  {
   "id": "enemy_1042_frostd",
   "prefabKey": "enemy_1042_frostd",
   "level": 0,
   "min_count": 0,
   "max_count": 0,
   "elite_min_count": 0,
   "elite_max_count": 0,
   "overwrittenData": null
  },
  {
   "id": "enemy_2101_dyspll",
   "prefabKey": "enemy_2101_dyspll",
   "level": 0,
   "min_count": 0,
   "max_count": 0,
   "elite_min_count": 0,
   "elite_max_count": 0,
   "overwrittenData": null
  },
  {
   "id": "enemy_2121_dyspl2",
   "prefabKey": "enemy_2121_dyspl2",
   "level": 0,
   "min_count": 0,
   "max_count": 0,
   "elite_min_count": 0,
   "elite_max_count": 0,
   "overwrittenData": null
  },
  {
   "id": "enemy_2119_dyshhj_2",
   "prefabKey": "enemy_2119_dyshhj_2",
   "level": 0,
   "min_count": 0,
   "max_count": 0,
   "elite_min_count": 0,
   "elite_max_count": 0,
   "overwrittenData": null
  },
  {
   "id": "enemy_2115_dylbg2",
   "prefabKey": "enemy_2115_dylbg2",
   "level": 0,
   "min_count": 0,
   "max_count": 0,
   "elite_min_count": 0,
   "elite_max_count": 0,
   "overwrittenData": {
    "talentBlackboard": [
     {
      "key": "dylbg2_heal",
      "atk": {
       "multiplier": 1.2
      }
     }
    ]
   }
  },
  {
   "id": "enemy_2113_dyhlg2",
   "prefabKey": "enemy_2113_dyhlg2",
   "level": 0,
   "min_count": 0,
   "max_count": 0,
   "elite_min_count": 0,
   "elite_max_count": 0,
   "overwrittenData": {
    "talentBlackboard": [
     {
      "key": "yan_statue_standby",
      "standby": 60
     }
    ]
   }
  },
  {
   "id": "enemy_2111_dyyrz2",
   "prefabKey": "enemy_2111_dyyrz2",
   "level": 0,
   "min_count": 0,
   "max_count": 0,
   "elite_min_count": 0,
   "elite_max_count": 0,
   "overwrittenData": null
  }
 ],
 "routes": [
  {
   "motionMode": "WALK",
   "startPosition": {
    "row": 5,
    "col": 7
   },
   "endPosition": {
    "row": 6,
    "col": 6
   },
   "spawnRandomRange": {
    "x": 0.0,
    "y": 0.0
   },
   "spawnOffset": {
    "x": 0.0,
    "y": 0.0
   },
   "checkpoints": [
    {
     "type": "WAIT_FOR_SECONDS",
     "time": 35.0,
     "position": {
      "row": 0,
      "col": 0
     },
     "reachOffset": {
      "x": 0.0,
      "y": 0.0
     },
     "reachDistance": 0.0
    },
    {
     "type": "MOVE",
     "time": 0.0,
     "position": {
      "row": 2,
      "col": 7
     },
     "reachOffset": {
      "x": 0.14,
      "y": -0.09
     },
     "reachDistance": 0.0
    },
    {
     "type": "WAIT_FOR_SECONDS",
     "time": 20.0,
     "position": {
      "row": 0,
      "col": 0
     },
     "reachOffset": {
      "x": 0.0,
      "y": 0.0
     },
     "reachDistance": 0.0
    },
    {
     "type": "MOVE",
     "time": 0.0,
     "position": {
      "row": 5,
      "col": 5
     },
     "reachOffset": {
      "x": 0.0,
      "y": 0.0
     },
     "reachDistance": 0.0
    },
    {
     "type": "WAIT_FOR_SECONDS",
     "time": 20.0,
     "position": {
      "row": 0,
      "col": 0
     },
     "reachOffset": {
      "x": 0.0,
      "y": 0.0
     },
     "reachDistance": 0.0
    },
    {
     "type": "MOVE",
     "time": 0.0,
     "position": {
      "row": 5,
      "col": 7
     },
     "reachOffset": {
      "x": 0.0,
      "y": 0.0
     },
     "reachDistance": 0.0
    },
    {
     "type": "WAIT_FOR_SECONDS",
     "time": 20.0,
     "position": {
      "row": 0,
      "col": 0
     },
     "reachOffset": {
      "x": 0.0,
      "y": 0.0
     },
     "reachDistance": 0.0
    }
   ],
   "allowDiagonalMove": true,
   "visitEveryTileCenter": false,
   "visitEveryNodeCenter": false,
   "visitEveryCheckPoint": false
  },
  {
   "motionMode": "WALK",
   "startPosition": {
    "row": 5,
    "col": 1
   },
   "endPosition": {
    "row": 0,
    "col": 6
   },
   "spawnRandomRange": {
    "x": 0.0,
    "y": 0.0
   },
   "spawnOffset": {
    "x": 0.0,
    "y": 0.0
   },
   "checkpoints": [
    {
     "type": "WAIT_FOR_SECONDS",
     "time": 60.0,
     "position": {
      "row": 0,
      "col": 0
     },
     "reachOffset": {
      "x": 0.0,
      "y": 0.0
     },
     "reachDistance": 0.0
    },
    {
     "type": "MOVE",
     "time": 0.0,
     "position": {
      "row": 5,
      "col": 0
     },
     "reachOffset": {
      "x": 0.0,
      "y": 0.0
     },
     "reachDistance": 0.0
    },
    {
     "type": "DISAPPEAR",
     "time": 0.0,
     "position": {
      "row": 0,
      "col": 0
     },
     "reachOffset": {
      "x": 0.0,
      "y": 0.0
     },
     "reachDistance": 0.0
    },
    {
     "type": "WAIT_FOR_SECONDS",
     "time": 5.0,
     "position": {
      "row": 0,
      "col": 0
     },
     "reachOffset": {
      "x": 0.0,
      "y": 0.0
     },
     "reachDistance": 0.0
    },
    {
     "type": "APPEAR_AT_POS",
     "time": 0.0,
     "position": {
      "row": 5,
      "col": 8
     },
     "reachOffset": {
      "x": 0.0,
      "y": 0.0
     },
     "reachDistance": 0.0
    },
    {
     "type": "MOVE",
     "time": 0.0,
     "position": {
      "row": 5,
      "col": 6
     },
     "reachOffset": {
      "x": 0.0,
      "y": 0.0
     },
     "reachDistance": 0.0
    },
    {
     "type": "MOVE",
     "time": 0.0,
     "position": {
      "row": 2,
      "col": 6
     },
     "reachOffset": {
      "x": 0.0,
      "y": 0.0
     },
     "reachDistance": 0.0
    },
    {
     "type": "MOVE",
     "time": 0.0,
     "position": {
      "row": 2,
      "col": 5
     },
     "reachOffset": {
      "x": 0.0,
      "y": 0.0
     },
     "reachDistance": 0.0
    },
    {
     "type": "MOVE",
     "time": 0.0,
     "position": {
      "row": 3,
      "col": 5
     },
     "reachOffset": {
      "x": 0.0,
      "y": 0.0
     },
     "reachDistance": 0.0
    },
    {
     "type": "MOVE",
     "time": 0.0,
     "position": {
      "row": 3,
      "col": 7
     },
     "reachOffset": {
      "x": 0.0,
      "y": 0.0
     },
     "reachDistance": 0.0
    },
    {
     "type": "MOVE",
     "time": 0.0,
     "position": {
      "row": 2,
      "col": 7
     },
     "reachOffset": {
      "x": 0.0,
      "y": 0.0
     },
     "reachDistance": 0.0
    },
    {
     "type": "MOVE",
     "time": 0.0,
     "position": {
      "row": 2,
      "col": 6
     },
     "reachOffset": {
      "x": 0.0,
      "y": 0.0
     },
     "reachDistance": 0.0
    }
   ],
   "allowDiagonalMove": true,
   "visitEveryTileCenter": false,
   "visitEveryNodeCenter": false,
   "visitEveryCheckPoint": false
  },
  {
   "motionMode": "WALK",
   "startPosition": {
    "row": 1,
    "col": 2
   },
   "endPosition": {
    "row": 0,
    "col": 6
   },
   "spawnRandomRange": {
    "x": 0.0,
    "y": 0.0
   },
   "spawnOffset": {
    "x": 0.0,
    "y": 0.0
   },
   "checkpoints": [
    {
     "type": "MOVE",
     "time": 0.0,
     "position": {
      "row": 1,
      "col": 3
     },
     "reachOffset": {
      "x": 0.0,
      "y": 0.0
     },
     "reachDistance": 0.0
    },
    {
     "type": "DISAPPEAR",
     "time": 0.0,
     "position": {
      "row": 0,
      "col": 0
     },
     "reachOffset": {
      "x": 0.0,
      "y": 0.0
     },
     "reachDistance": 0.0
    },
    {
     "type": "WAIT_FOR_SECONDS",
     "time": 5.0,
     "position": {
      "row": 0,
      "col": 0
     },
     "reachOffset": {
      "x": 0.0,
      "y": 0.0
     },
     "reachDistance": 0.0
    },
    {
     "type": "APPEAR_AT_POS",
     "time": 0.0,
     "position": {
      "row": 3,
      "col": 4
     },
     "reachOffset": {
      "x": 0.0,
      "y": 0.0
     },
     "reachDistance": 0.0
    },
    {
     "type": "WAIT_FOR_SECONDS",
     "time": 50.0,
     "position": {
      "row": 0,
      "col": 0
     },
     "reachOffset": {
      "x": 0.0,
      "y": 0.0
     },
     "reachDistance": 0.0
    },
    {
     "type": "MOVE",
     "time": 0.0,
     "position": {
      "row": 3,
      "col": 6
     },
     "reachOffset": {
      "x": 0.0,
      "y": 0.0
     },
     "reachDistance": 0.0
    }
   ],
   "allowDiagonalMove": true,
   "visitEveryTileCenter": false,
   "visitEveryNodeCenter": false,
   "visitEveryCheckPoint": false
  },
  {
   "motionMode": "WALK",
   "startPosition": {
    "row": 5,
    "col": 6
   },
   "endPosition": {
    "row": 0,
    "col": 6
   },
   "spawnRandomRange": {
    "x": 0.0,
    "y": 0.0
   },
   "spawnOffset": {
    "x": 0.0,
    "y": 0.0
   },
   "checkpoints": [
    {
     "type": "MOVE",
     "time": 0.0,
     "position": {
      "row": 5,
      "col": 6
     },
     "reachOffset": {
      "x": 0.0,
      "y": 0.0
     },
     "reachDistance": 0.0
    },
    {
     "type": "WAIT_FOR_SECONDS",
     "time": 5.0,
     "position": {
      "row": 0,
      "col": 0
     },
     "reachOffset": {
      "x": 0.0,
      "y": 0.0
     },
     "reachDistance": 0.0
    }
   ],
   "allowDiagonalMove": true,
   "visitEveryTileCenter": false,
   "visitEveryNodeCenter": false,
   "visitEveryCheckPoint": false
  },
  {
   "motionMode": "FLY",
   "startPosition": {
    "row": 3,
    "col": 8
   },
   "endPosition": {
    "row": 0,
    "col": 6
   },
   "spawnRandomRange": {
    "x": 0.0,
    "y": 0.0
   },
   "spawnOffset": {
    "x": 0.0,
    "y": 0.0
   },
   "checkpoints": [
    {
     "type": "MOVE",
     "time": 0.0,
     "position": {
      "row": 3,
      "col": 6
     },
     "reachOffset": {
      "x": 0.0,
      "y": 0.0
     },
     "reachDistance": 0.0
    },
    {
     "type": "WAIT_FOR_SECONDS",
     "time": 80.0,
     "position": {
      "row": 0,
      "col": 0
     },
     "reachOffset": {
      "x": 0.0,
      "y": 0.0
     },
     "reachDistance": 0.0
    }
   ],
   "allowDiagonalMove": true,
   "visitEveryTileCenter": false,
   "visitEveryNodeCenter": false,
   "visitEveryCheckPoint": false
  },
  {
   "motionMode": "FLY",
   "startPosition": {
    "row": 4,
    "col": 6
   },
   "endPosition": {
    "row": 3,
    "col": 7
   },
   "spawnRandomRange": {
    "x": 0.0,
    "y": 0.0
   },
   "spawnOffset": {
    "x": 0.0,
    "y": 0.0
   },
   "checkpoints": [
    {
     "type": "WAIT_FOR_SECONDS",
     "time": 999.0,
     "position": {
      "row": 0,
      "col": 0
     },
     "reachOffset": {
      "x": 0.0,
      "y": 0.0
     },
     "reachDistance": 0.0
    }
   ],
   "allowDiagonalMove": true,
   "visitEveryTileCenter": false,
   "visitEveryNodeCenter": false,
   "visitEveryCheckPoint": false
  },
  {
   "motionMode": "WALK",
   "startPosition": {
    "row": 6,
    "col": 6
   },
   "endPosition": {
    "row": 0,
    "col": 6
   },
   "spawnRandomRange": {
    "x": 0.0,
    "y": 0.0
   },
   "spawnOffset": {
    "x": 0.0,
    "y": 0.0
   },
   "checkpoints": [],
   "allowDiagonalMove": true,
   "visitEveryTileCenter": false,
   "visitEveryNodeCenter": false,
   "visitEveryCheckPoint": false
  }
 ],
 "mapData": {
  "map": [
   [
    54,
    55,
    56,
    57,
    58,
    59,
    60,
    61,
    62
   ],
   [
    45,
    46,
    47,
    48,
    49,
    50,
    51,
    52,
    53
   ],
   [
    36,
    37,
    38,
    39,
    40,
    41,
    42,
    43,
    44
   ],
   [
    27,
    28,
    29,
    30,
    31,
    32,
    33,
    34,
    35
   ],
   [
    18,
    19,
    20,
    21,
    22,
    23,
    24,
    25,
    26
   ],
   [
    9,
    10,
    11,
    12,
    13,
    14,
    15,
    16,
    17
   ],
   [
    0,
    1,
    2,
    3,
    4,
    5,
    6,
    7,
    8
   ]
  ],
  "tiles": [
   [
    "tile_forbidden",
    1,
    1,
    null,
    0
   ],
   [
    "tile_forbidden",
    1,
    1,
    null,
    0
   ],
   [
    "tile_forbidden",
    1,
    1,
    null,
    0
   ],
   [
    "tile_forbidden",
    1,
    1,
    null,
    0
   ],
   [
    "tile_forbidden",
    1,
    1,
    null,
    0
   ],
   [
    "tile_forbidden",
    1,
    1,
    null,
    0
   ],
   [
    "tile_end",
    0,
    0,
    null,
    0
   ],
   [
    "tile_forbidden",
    1,
    1,
    null,
    0
   ],
   [
    "tile_forbidden",
    1,
    1,
    null,
    0
   ],
   [
    "tile_forbidden",
    1,
    1,
    null,
    0
   ],
   [
    "tile_start",
    0,
    0,
    null,
    0
   ],
   [
    "tile_floor",
    0,
    0,
    null,
    0
   ],
   [
    "tile_telin",
    0,
    0,
    {
     "colorIndex": 0,
     "direction": "",
     "type": "arrow"
    },
    0
   ],
   [
    "tile_forbidden",
    1,
    1,
    null,
    0
   ],
   [
    "tile_wall",
    1,
    1,
    null,
    1
   ],
   [
    "tile_road",
    0,
    0,
    null,
    1
   ],
   [
    "tile_wall",
    1,
    1,
    null,
    1
   ],
   [
    "tile_forbidden",
    1,
    1,
    null,
    0
   ],
   [
    "tile_forbidden",
    1,
    1,
    null,
    0
   ],
   [
    "tile_forbidden",
    1,
    1,
    null,
    0
   ],
   [
    "tile_forbidden",
    1,
    1,
    null,
    0
   ],
   [
    "tile_forbidden",
    1,
    1,
    null,
    0
   ],
   [
    "tile_dygmny_3",
    1,
    1,
    null,
    1
   ],
   [
    "tile_road",
    0,
    0,
    null,
    1
   ],
   [
    "tile_road",
    0,
    0,
    null,
    1
   ],
   [
    "tile_road",
    0,
    0,
    null,
    1
   ],
   [
    "tile_forbidden",
    1,
    1,
    null,
    0
   ],
   [
    "tile_forbidden",
    1,
    1,
    null,
    0
   ],
   [
    "tile_forbidden",
    1,
    1,
    null,
    0
   ],
   [
    "tile_forbidden",
    1,
    1,
    null,
    0
   ],
   [
    "tile_forbidden",
    1,
    1,
    null,
    0
   ],
   [
    "tile_telout",
    0,
    0,
    {
     "colorIndex": 0,
     "direction": "",
     "type": "arrow"
    },
    0
   ],
   [
    "tile_road",
    0,
    0,
    null,
    1
   ],
   [
    "tile_road",
    0,
    0,
    null,
    1
   ],
   [
    "tile_road",
    0,
    0,
    null,
    1
   ],
   [
    "tile_flystart",
    1,
    1,
    null,
    0
   ],
   [
    "tile_forbidden",
    1,
    1,
    null,
    0
   ],
   [
    "tile_forbidden",
    1,
    1,
    null,
    0
   ],
   [
    "tile_forbidden",
    1,
    1,
    null,
    0
   ],
   [
    "tile_forbidden",
    1,
    1,
    null,
    0
   ],
   [
    "tile_dygmny_3",
    1,
    1,
    null,
    1
   ],
   [
    "tile_dygmny_1",
    0,
    0,
    null,
    1
   ],
   [
    "tile_dygmny_1",
    0,
    0,
    null,
    1
   ],
   [
    "tile_dygmny_1",
    0,
    0,
    null,
    1
   ],
   [
    "tile_forbidden",
    1,
    1,
    null,
    0
   ],
   [
    "tile_telin",
    0,
    0,
    {
     "colorIndex": 0,
     "direction": "",
     "type": "arrow"
    },
    0
   ],
   [
    "tile_floor",
    0,
    0,
    null,
    0
   ],
   [
    "tile_forbidden",
    1,
    1,
    null,
    0
   ],
   [
    "tile_forbidden",
    1,
    1,
    null,
    0
   ],
   [
    "tile_fence_bound",
    0,
    1,
    null,
    1
   ],
   [
    "tile_floor",
    0,
    0,
    null,
    0
   ],
   [
    "tile_floor",
    0,
    0,
    null,
    0
   ],
   [
    "tile_floor",
    0,
    0,
    null,
    0
   ],
   [
    "tile_telout",
    0,
    0,
    {
     "colorIndex": 0,
     "direction": "",
     "type": "arrow"
    },
    0
   ],
   [
    "tile_forbidden",
    1,
    1,
    null,
    0
   ],
   [
    "tile_forbidden",
    1,
    1,
    null,
    0
   ],
   [
    "tile_forbidden",
    1,
    1,
    null,
    0
   ],
   [
    "tile_forbidden",
    1,
    1,
    null,
    0
   ],
   [
    "tile_forbidden",
    1,
    1,
    null,
    0
   ],
   [
    "tile_forbidden",
    1,
    1,
    null,
    0
   ],
   [
    "tile_start",
    0,
    0,
    null,
    0
   ],
   [
    "tile_forbidden",
    1,
    1,
    null,
    0
   ],
   [
    "tile_forbidden",
    1,
    1,
    null,
    0
   ]
  ]
 },
 "extra_routes": [],
 "branches": null,
 "NORMAL": {
  "groupKey": null,
  "max_permutations": 1,
  "permutations": [
   {}
  ]
 },
 "ELITE": {
  "groupKey": null,
  "max_permutations": 1,
  "permutations": [
   {}
  ]
 },
 "waves": [
  {
   "preDelay": 0.0,
   "postDelay": 0.0,
   "maxTimeWaitingForNextWave": -1.0,
   "fragments": [
    {
     "preDelay": 0.0,
     "actions": [
      {
       "actionType": "SPAWN",
       "key": "enemy_2034_sythef",
       "count": 1,
       "preDelay": 0.0,
       "interval": 1.0,
       "routeIndex": 0,
       "autoPreviewRoute": true,
       "hiddenGroup": null,
       "randomSpawnGroupKey": null,
       "randomSpawnGroupPackKey": null,
       "weight": 5,
       "dontBlockWave": false
      },
      {
       "actionType": "SPAWN",
       "key": "enemy_2113_dyhlg2",
       "count": 1,
       "preDelay": 0.0,
       "interval": 1.0,
       "routeIndex": 1,
       "autoPreviewRoute": false,
       "hiddenGroup": null,
       "randomSpawnGroupKey": null,
       "randomSpawnGroupPackKey": null,
       "weight": 50,
       "dontBlockWave": false
      },
      {
       "actionType": "SPAWN",
       "key": "enemy_2115_dylbg2",
       "count": 1,
       "preDelay": 0.0,
       "interval": 1.0,
       "routeIndex": 2,
       "autoPreviewRoute": false,
       "hiddenGroup": null,
       "randomSpawnGroupKey": null,
       "randomSpawnGroupPackKey": null,
       "weight": 0,
       "dontBlockWave": false
      },
      {
       "actionType": "SPAWN",
       "key": "enemy_2111_dyyrz2",
       "count": 1,
       "preDelay": 0.0,
       "interval": 1.0,
       "routeIndex": 3,
       "autoPreviewRoute": false,
       "hiddenGroup": null,
       "randomSpawnGroupKey": null,
       "randomSpawnGroupPackKey": null,
       "weight": 0,
       "dontBlockWave": false
      },
      {
       "actionType": "SPAWN",
       "key": "enemy_1042_frostd",
       "count": 1,
       "preDelay": 100.0,
       "interval": 1.0,
       "routeIndex": 4,
       "autoPreviewRoute": false,
       "hiddenGroup": null,
       "randomSpawnGroupKey": null,
       "randomSpawnGroupPackKey": null,
       "weight": 0,
       "dontBlockWave": false
      },
      {
       "actionType": "SPAWN",
       "key": "enemy_2119_dyshhj_2",
       "count": 1,
       "preDelay": 0.0,
       "interval": 1.0,
       "routeIndex": 5,
       "autoPreviewRoute": false,
       "hiddenGroup": "copper_b",
       "randomSpawnGroupKey": null,
       "randomSpawnGroupPackKey": null,
       "weight": 0,
       "dontBlockWave": true
      },
      {
       "actionType": "SPAWN",
       "key": "enemy_2001_duckmi",
       "count": 1,
       "preDelay": 160.0,
       "interval": 1.0,
       "routeIndex": 6,
       "autoPreviewRoute": false,
       "hiddenGroup": "copper_r",
       "randomSpawnGroupKey": "tel",
       "randomSpawnGroupPackKey": null,
       "weight": 5,
       "dontBlockWave": false
      },
      {
       "actionType": "SPAWN",
       "key": "enemy_2002_bearmi",
       "count": 1,
       "preDelay": 160.0,
       "interval": 1.0,
       "routeIndex": 6,
       "autoPreviewRoute": false,
       "hiddenGroup": "copper_r",
       "randomSpawnGroupKey": "tel",
       "randomSpawnGroupPackKey": null,
       "weight": 5,
       "dontBlockWave": false
      },
      {
       "actionType": "SPAWN",
       "key": "enemy_2085_skzjxd",
       "count": 1,
       "preDelay": 160.0,
       "interval": 1.0,
       "routeIndex": 6,
       "autoPreviewRoute": false,
       "hiddenGroup": "copper_r",
       "randomSpawnGroupKey": "tel",
       "randomSpawnGroupPackKey": null,
       "weight": 5,
       "dontBlockWave": false
      }
     ]
    }
   ],
   "advancedWaveTag": null
  }
 ],
 "bonus": {
  "type": "wave",
  "wave_index": 0,
  "frag_index": -1
 }
}