{
 "id": "act28side_ex02",
 "levelId": "act28side_ex02",
 "tags": null,
 "category": null,
 "characterLimit": 8,
 "initialCost": 10,
 "maxCost": 99,
 "costIncreaseTime": 1.0,
 "code": "CV-EX-2",
 "name_zh": "打开保险",
 "name_ja": "セーフティ解除",
 "name_en": "Release the Safety",
 "description_zh": "当做出这样的决定时，一切都不再安全。\n<@lv.item><废热喷口></>造成无视敌我的法术伤害并减速敌人，但会使敌人能量增加",
 "description_ja": "その決断を下した瞬間から、もはやどこも安全ではなくなる。\n<@lv.item><廃熱噴出口></>熱噴射により前方一定範囲内の敵味方全員に術ダメージを与える。熱噴射を受けている敵は減速するが、エネルギーが持続的にチャージされる",
 "description_en": "Once you've made a decision like that, nowhere is safe anymore.\n<@lv.item><Waste Heat Vent></> Deals Arts damage to both enemies and allies and reduces enemies' Movement Speed, but will charge their energy.",
 "addInfo_zh": null,
 "addInfo_ja": null,
 "addInfo_en": null,
 "eliteDesc_zh": null,
 "eliteDesc_ja": null,
 "eliteDesc_en": null,
 "n_mods": null,
 "elite_mods": null,
 "floors": null,
 "sp_terrain": null,
 "sp_enemy": null,
 "n_count": null,
 "e_count": null,
 "traps": [
  {
   "key": "trap_124_eradio",
   "alias": "trap_124_eradio#1",
   "pos": {
    "row": 1,
    "col": 3
   },
   "direction": "UP",
   "level": 1,
   "mainSkillLvl": 1,
   "hidden": false
  },
  {
   "key": "trap_124_eradio",
   "alias": "trap_124_eradio#2",
   "pos": {
    "row": 6,
    "col": 8
   },
   "direction": "LEFT",
   "level": 1,
   "mainSkillLvl": 1,
   "hidden": false
  },
  {
   "key": "trap_124_eradio",
   "alias": "trap_124_eradio#3",
   "pos": {
    "row": 1,
    "col": 6
   },
   "direction": "UP",
   "level": 1,
   "mainSkillLvl": 1,
   "hidden": false
  },
  {
   "key": "trap_124_eradio",
   "alias": "trap_124_eradio#4",
   "pos": {
    "row": 6,
    "col": 7
   },
   "direction": "LEFT",
   "level": 1,
   "mainSkillLvl": 1,
   "hidden": false
  },
  {
   "key": "trap_124_eradio",
   "alias": "trap_124_eradio#5",
   "pos": {
    "row": 2,
    "col": 5
   },
   "direction": "RIGHT",
   "level": 1,
   "mainSkillLvl": 1,
   "hidden": false
  },
  {
   "key": "trap_124_eradio",
   "alias": "trap_124_eradio#6",
   "pos": {
    "row": 2,
    "col": 4
   },
   "direction": "RIGHT",
   "level": 1,
   "mainSkillLvl": 1,
   "hidden": false
  }
 ],
 "token_cards": [],
 "enemies": [
  {
   "id": "enemy_1353_esabr_2",
   "prefabKey": "enemy_1353_esabr_2",
   "level": 0,
   "min_count": 0,
   "max_count": 0,
   "elite_min_count": 0,
   "elite_max_count": 0,
   "overwrittenData": null
  },
  {
   "id": "enemy_1354_eghost_2",
   "prefabKey": "enemy_1354_eghost_2",
   "level": 0,
   "min_count": 0,
   "max_count": 0,
   "elite_min_count": 0,
   "elite_max_count": 0,
   "overwrittenData": null
  },
  {
   "id": "enemy_1355_mrfly_2",
   "prefabKey": "enemy_1355_mrfly_2",
   "level": 0,
   "min_count": 0,
   "max_count": 0,
   "elite_min_count": 0,
   "elite_max_count": 0,
   "overwrittenData": null
  },
  {
   "id": "enemy_1356_egun_2",
   "prefabKey": "enemy_1356_egun_2",
   "level": 0,
   "min_count": 0,
   "max_count": 0,
   "elite_min_count": 0,
   "elite_max_count": 0,
   "overwrittenData": null
  },
  {
   "id": "enemy_1358_esheld_2",
   "prefabKey": "enemy_1358_esheld_2",
   "level": 0,
   "min_count": 0,
   "max_count": 0,
   "elite_min_count": 0,
   "elite_max_count": 0,
   "overwrittenData": null
  }
 ],
 "routes": [
  {
   "motionMode": "FLY",
   "startPosition": {
    "row": 4,
    "col": 2
   },
   "endPosition": {
    "row": 4,
    "col": 10
   },
   "spawnRandomRange": {
    "x": 0.0,
    "y": 0.0
   },
   "spawnOffset": {
    "x": 0.0,
    "y": 0.0
   },
   "checkpoints": [
    {
     "type": "MOVE",
     "time": 0.0,
     "position": {
      "row": 4,
      "col": 5
     },
     "reachOffset": {
      "x": 0.0,
      "y": 0.0
     },
     "reachDistance": 0.0
    },
    {
     "type": "WAIT_FOR_SECONDS",
     "time": 120.0,
     "position": {
      "row": 0,
      "col": 0
     },
     "reachOffset": {
      "x": 0.0,
      "y": 0.0
     },
     "reachDistance": 0.0
    }
   ],
   "allowDiagonalMove": true,
   "visitEveryTileCenter": false,
   "visitEveryNodeCenter": false,
   "visitEveryCheckPoint": false
  },
  {
   "motionMode": "WALK",
   "startPosition": {
    "row": 7,
    "col": 1
   },
   "endPosition": {
    "row": 4,
    "col": 10
   },
   "spawnRandomRange": {
    "x": 0.0,
    "y": 0.0
   },
   "spawnOffset": {
    "x": 0.0,
    "y": 0.0
   },
   "checkpoints": [],
   "allowDiagonalMove": true,
   "visitEveryTileCenter": false,
   "visitEveryNodeCenter": false,
   "visitEveryCheckPoint": false
  },
  {
   "motionMode": "WALK",
   "startPosition": {
    "row": 7,
    "col": 1
   },
   "endPosition": {
    "row": 4,
    "col": 10
   },
   "spawnRandomRange": {
    "x": 0.0,
    "y": 0.0
   },
   "spawnOffset": {
    "x": 0.0,
    "y": 0.0
   },
   "checkpoints": [
    {
     "type": "MOVE",
     "time": 0.0,
     "position": {
      "row": 6,
      "col": 1
     },
     "reachOffset": {
      "x": 0.0,
      "y": 0.0
     },
     "reachDistance": 0.0
    },
    {
     "type": "WAIT_FOR_SECONDS",
     "time": 10.0,
     "position": {
      "row": 0,
      "col": 0
     },
     "reachOffset": {
      "x": 0.0,
      "y": 0.0
     },
     "reachDistance": 0.0
    }
   ],
   "allowDiagonalMove": true,
   "visitEveryTileCenter": false,
   "visitEveryNodeCenter": false,
   "visitEveryCheckPoint": false
  },
  {
   "motionMode": "WALK",
   "startPosition": {
    "row": 7,
    "col": 1
   },
   "endPosition": {
    "row": 4,
    "col": 10
   },
   "spawnRandomRange": {
    "x": 0.0,
    "y": 0.0
   },
   "spawnOffset": {
    "x": 0.0,
    "y": 0.0
   },
   "checkpoints": [
    {
     "type": "MOVE",
     "time": 0.0,
     "position": {
      "row": 5,
      "col": 1
     },
     "reachOffset": {
      "x": 0.0,
      "y": 0.0
     },
     "reachDistance": 0.0
    },
    {
     "type": "WAIT_FOR_SECONDS",
     "time": 10.0,
     "position": {
      "row": 0,
      "col": 0
     },
     "reachOffset": {
      "x": 0.0,
      "y": 0.0
     },
     "reachDistance": 0.0
    }
   ],
   "allowDiagonalMove": true,
   "visitEveryTileCenter": false,
   "visitEveryNodeCenter": false,
   "visitEveryCheckPoint": false
  },
  {
   "motionMode": "WALK",
   "startPosition": {
    "row": 7,
    "col": 1
   },
   "endPosition": {
    "row": 4,
    "col": 10
   },
   "spawnRandomRange": {
    "x": 0.0,
    "y": 0.0
   },
   "spawnOffset": {
    "x": 0.0,
    "y": 0.0
   },
   "checkpoints": [
    {
     "type": "MOVE",
     "time": 0.0,
     "position": {
      "row": 4,
      "col": 1
     },
     "reachOffset": {
      "x": 0.0,
      "y": 0.0
     },
     "reachDistance": 0.0
    },
    {
     "type": "WAIT_FOR_SECONDS",
     "time": 10.0,
     "position": {
      "row": 0,
      "col": 0
     },
     "reachOffset": {
      "x": 0.0,
      "y": 0.0
     },
     "reachDistance": 0.0
    }
   ],
   "allowDiagonalMove": true,
   "visitEveryTileCenter": false,
   "visitEveryNodeCenter": false,
   "visitEveryCheckPoint": false
  },
  {
   "motionMode": "WALK",
   "startPosition": {
    "row": 3,
    "col": 0
   },
   "endPosition": {
    "row": 4,
    "col": 10
   },
   "spawnRandomRange": {
    "x": 0.0,
    "y": 0.0
   },
   "spawnOffset": {
    "x": 0.0,
    "y": 0.0
   },
   "checkpoints": [
    {
     "type": "MOVE",
     "time": 0.0,
     "position": {
      "row": 3,
      "col": 2
     },
     "reachOffset": {
      "x": 0.0,
      "y": 0.0
     },
     "reachDistance": 0.0
    },
    {
     "type": "WAIT_FOR_SECONDS",
     "time": 30.0,
     "position": {
      "row": 0,
      "col": 0
     },
     "reachOffset": {
      "x": 0.0,
      "y": 0.0
     },
     "reachDistance": 0.0
    }
   ],
   "allowDiagonalMove": true,
   "visitEveryTileCenter": false,
   "visitEveryNodeCenter": false,
   "visitEveryCheckPoint": false
  },
  {
   "motionMode": "WALK",
   "startPosition": {
    "row": 2,
    "col": 0
   },
   "endPosition": {
    "row": 4,
    "col": 10
   },
   "spawnRandomRange": {
    "x": 0.0,
    "y": 0.0
   },
   "spawnOffset": {
    "x": 0.0,
    "y": 0.0
   },
   "checkpoints": [
    {
     "type": "MOVE",
     "time": 0.0,
     "position": {
      "row": 2,
      "col": 2
     },
     "reachOffset": {
      "x": 0.0,
      "y": 0.0
     },
     "reachDistance": 0.0
    },
    {
     "type": "WAIT_FOR_SECONDS",
     "time": 30.0,
     "position": {
      "row": 0,
      "col": 0
     },
     "reachOffset": {
      "x": 0.0,
      "y": 0.0
     },
     "reachDistance": 0.0
    }
   ],
   "allowDiagonalMove": true,
   "visitEveryTileCenter": false,
   "visitEveryNodeCenter": false,
   "visitEveryCheckPoint": false
  },
  {
   "motionMode": "WALK",
   "startPosition": {
    "row": 3,
    "col": 0
   },
   "endPosition": {
    "row": 4,
    "col": 10
   },
   "spawnRandomRange": {
    "x": 0.0,
    "y": 0.0
   },
   "spawnOffset": {
    "x": 0.0,
    "y": 0.0
   },
   "checkpoints": [
    {
     "type": "MOVE",
     "time": 0.0,
     "position": {
      "row": 3,
      "col": 1
     },
     "reachOffset": {
      "x": 0.0,
      "y": 0.0
     },
     "reachDistance": 0.0
    },
    {
     "type": "WAIT_FOR_SECONDS",
     "time": 30.0,
     "position": {
      "row": 0,
      "col": 0
     },
     "reachOffset": {
      "x": 0.0,
      "y": 0.0
     },
     "reachDistance": 0.0
    }
   ],
   "allowDiagonalMove": true,
   "visitEveryTileCenter": false,
   "visitEveryNodeCenter": false,
   "visitEveryCheckPoint": false
  },
  {
   "motionMode": "WALK",
   "startPosition": {
    "row": 2,
    "col": 0
   },
   "endPosition": {
    "row": 4,
    "col": 10
   },
   "spawnRandomRange": {
    "x": 0.0,
    "y": 0.0
   },
   "spawnOffset": {
    "x": 0.0,
    "y": 0.0
   },
   "checkpoints": [
    {
     "type": "MOVE",
     "time": 0.0,
     "position": {
      "row": 2,
      "col": 1
     },
     "reachOffset": {
      "x": 0.0,
      "y": 0.0
     },
     "reachDistance": 0.0
    },
    {
     "type": "WAIT_FOR_SECONDS",
     "time": 30.0,
     "position": {
      "row": 0,
      "col": 0
     },
     "reachOffset": {
      "x": 0.0,
      "y": 0.0
     },
     "reachDistance": 0.0
    }
   ],
   "allowDiagonalMove": true,
   "visitEveryTileCenter": false,
   "visitEveryNodeCenter": false,
   "visitEveryCheckPoint": false
  },
  {
   "motionMode": "WALK",
   "startPosition": {
    "row": 3,
    "col": 0
   },
   "endPosition": {
    "row": 4,
    "col": 10
   },
   "spawnRandomRange": {
    "x": 0.0,
    "y": 0.0
   },
   "spawnOffset": {
    "x": 0.0,
    "y": 0.0
   },
   "checkpoints": [
    {
     "type": "MOVE",
     "time": 0.0,
     "position": {
      "row": 3,
      "col": 2
     },
     "reachOffset": {
      "x": 0.0,
      "y": 0.0
     },
     "reachDistance": 0.0
    },
    {
     "type": "WAIT_FOR_SECONDS",
     "time": 40.0,
     "position": {
      "row": 0,
      "col": 0
     },
     "reachOffset": {
      "x": 0.0,
      "y": 0.0
     },
     "reachDistance": 0.0
    }
   ],
   "allowDiagonalMove": true,
   "visitEveryTileCenter": false,
   "visitEveryNodeCenter": false,
   "visitEveryCheckPoint": false
  },
  {
   "motionMode": "WALK",
   "startPosition": {
    "row": 3,
    "col": 0
   },
   "endPosition": {
    "row": 4,
    "col": 10
   },
   "spawnRandomRange": {
    "x": 0.0,
    "y": 0.0
   },
   "spawnOffset": {
    "x": 0.0,
    "y": 0.0
   },
   "checkpoints": [
    {
     "type": "MOVE",
     "time": 0.0,
     "position": {
      "row": 3,
      "col": 1
     },
     "reachOffset": {
      "x": 0.0,
      "y": 0.0
     },
     "reachDistance": 0.0
    },
    {
     "type": "WAIT_FOR_SECONDS",
     "time": 20.0,
     "position": {
      "row": 0,
      "col": 0
     },
     "reachOffset": {
      "x": 0.0,
      "y": 0.0
     },
     "reachDistance": 0.0
    }
   ],
   "allowDiagonalMove": true,
   "visitEveryTileCenter": false,
   "visitEveryNodeCenter": false,
   "visitEveryCheckPoint": false
  },
  {
   "motionMode": "WALK",
   "startPosition": {
    "row": 2,
    "col": 0
   },
   "endPosition": {
    "row": 4,
    "col": 10
   },
   "spawnRandomRange": {
    "x": 0.0,
    "y": 0.0
   },
   "spawnOffset": {
    "x": 0.0,
    "y": 0.0
   },
   "checkpoints": [
    {
     "type": "MOVE",
     "time": 0.0,
     "position": {
      "row": 2,
      "col": 2
     },
     "reachOffset": {
      "x": 0.0,
      "y": 0.0
     },
     "reachDistance": 0.0
    },
    {
     "type": "WAIT_FOR_SECONDS",
     "time": 20.0,
     "position": {
      "row": 0,
      "col": 0
     },
     "reachOffset": {
      "x": 0.0,
      "y": 0.0
     },
     "reachDistance": 0.0
    }
   ],
   "allowDiagonalMove": true,
   "visitEveryTileCenter": false,
   "visitEveryNodeCenter": false,
   "visitEveryCheckPoint": false
  },
  {
   "motionMode": "WALK",
   "startPosition": {
    "row": 2,
    "col": 0
   },
   "endPosition": {
    "row": 4,
    "col": 10
   },
   "spawnRandomRange": {
    "x": 0.0,
    "y": 0.0
   },
   "spawnOffset": {
    "x": 0.0,
    "y": 0.0
   },
   "checkpoints": [
    {
     "type": "MOVE",
     "time": 0.0,
     "position": {
      "row": 2,
      "col": 1
     },
     "reachOffset": {
      "x": 0.0,
      "y": 0.0
     },
     "reachDistance": 0.0
    },
    {
     "type": "WAIT_FOR_SECONDS",
     "time": 20.0,
     "position": {
      "row": 0,
      "col": 0
     },
     "reachOffset": {
      "x": 0.0,
      "y": 0.0
     },
     "reachDistance": 0.0
    }
   ],
   "allowDiagonalMove": true,
   "visitEveryTileCenter": false,
   "visitEveryNodeCenter": false,
   "visitEveryCheckPoint": false
  },
  {
   "motionMode": "WALK",
   "startPosition": {
    "row": 7,
    "col": 1
   },
   "endPosition": {
    "row": 4,
    "col": 10
   },
   "spawnRandomRange": {
    "x": 0.0,
    "y": 0.0
   },
   "spawnOffset": {
    "x": 0.0,
    "y": 0.0
   },
   "checkpoints": [
    {
     "type": "MOVE",
     "time": 0.0,
     "position": {
      "row": 4,
      "col": 1
     },
     "reachOffset": {
      "x": 0.0,
      "y": 0.0
     },
     "reachDistance": 0.0
    },
    {
     "type": "WAIT_FOR_SECONDS",
     "time": 30.0,
     "position": {
      "row": 0,
      "col": 0
     },
     "reachOffset": {
      "x": 0.0,
      "y": 0.0
     },
     "reachDistance": 0.0
    }
   ],
   "allowDiagonalMove": true,
   "visitEveryTileCenter": false,
   "visitEveryNodeCenter": false,
   "visitEveryCheckPoint": false
  },
  {
   "motionMode": "WALK",
   "startPosition": {
    "row": 7,
    "col": 1
   },
   "endPosition": {
    "row": 4,
    "col": 10
   },
   "spawnRandomRange": {
    "x": 0.0,
    "y": 0.0
   },
   "spawnOffset": {
    "x": 0.0,
    "y": 0.0
   },
   "checkpoints": [
    {
     "type": "MOVE",
     "time": 0.0,
     "position": {
      "row": 5,
      "col": 1
     },
     "reachOffset": {
      "x": 0.0,
      "y": 0.0
     },
     "reachDistance": 0.0
    },
    {
     "type": "WAIT_FOR_SECONDS",
     "time": 30.0,
     "position": {
      "row": 0,
      "col": 0
     },
     "reachOffset": {
      "x": 0.0,
      "y": 0.0
     },
     "reachDistance": 0.0
    }
   ],
   "allowDiagonalMove": true,
   "visitEveryTileCenter": false,
   "visitEveryNodeCenter": false,
   "visitEveryCheckPoint": false
  },
  {
   "motionMode": "WALK",
   "startPosition": {
    "row": 7,
    "col": 1
   },
   "endPosition": {
    "row": 4,
    "col": 10
   },
   "spawnRandomRange": {
    "x": 0.0,
    "y": 0.0
   },
   "spawnOffset": {
    "x": 0.0,
    "y": 0.0
   },
   "checkpoints": [
    {
     "type": "MOVE",
     "time": 0.0,
     "position": {
      "row": 6,
      "col": 1
     },
     "reachOffset": {
      "x": 0.0,
      "y": 0.0
     },
     "reachDistance": 0.0
    },
    {
     "type": "WAIT_FOR_SECONDS",
     "time": 30.0,
     "position": {
      "row": 0,
      "col": 0
     },
     "reachOffset": {
      "x": 0.0,
      "y": 0.0
     },
     "reachDistance": 0.0
    }
   ],
   "allowDiagonalMove": true,
   "visitEveryTileCenter": false,
   "visitEveryNodeCenter": false,
   "visitEveryCheckPoint": false
  },
  {
   "motionMode": "FLY",
   "startPosition": {
    "row": 4,
    "col": 2
   },
   "endPosition": {
    "row": 4,
    "col": 10
   },
   "spawnRandomRange": {
    "x": 0.0,
    "y": 0.0
   },
   "spawnOffset": {
    "x": 0.0,
    "y": 0.0
   },
   "checkpoints": [
    {
     "type": "MOVE",
     "time": 0.0,
     "position": {
      "row": 4,
      "col": 7
     },
     "reachOffset": {
      "x": 0.0,
      "y": 0.0
     },
     "reachDistance": 0.0
    },
    {
     "type": "WAIT_FOR_SECONDS",
     "time": 40.0,
     "position": {
      "row": 0,
      "col": 0
     },
     "reachOffset": {
      "x": 0.0,
      "y": 0.0
     },
     "reachDistance": 0.0
    }
   ],
   "allowDiagonalMove": true,
   "visitEveryTileCenter": false,
   "visitEveryNodeCenter": false,
   "visitEveryCheckPoint": false
  }
 ],
 "mapData": {
  "map": [
   [
    84,
    85,
    86,
    87,
    88,
    89,
    90,
    91,
    92,
    93,
    94,
    95
   ],
   [
    72,
    73,
    74,
    75,
    76,
    77,
    78,
    79,
    80,
    81,
    82,
    83
   ],
   [
    60,
    61,
    62,
    63,
    64,
    65,
    66,
    67,
    68,
    69,
    70,
    71
   ],
   [
    48,
    49,
    50,
    51,
    52,
    53,
    54,
    55,
    56,
    57,
    58,
    59
   ],
   [
    36,
    37,
    38,
    39,
    40,
    41,
    42,
    43,
    44,
    45,
    46,
    47
   ],
   [
    24,
    25,
    26,
    27,
    28,
    29,
    30,
    31,
    32,
    33,
    34,
    35
   ],
   [
    12,
    13,
    14,
    15,
    16,
    17,
    18,
    19,
    20,
    21,
    22,
    23
   ],
   [
    0,
    1,
    2,
    3,
    4,
    5,
    6,
    7,
    8,
    9,
    10,
    11
   ]
  ],
  "tiles": [
   [
    "tile_forbidden",
    1,
    1,
    null,
    0
   ],
   [
    "tile_forbidden",
    1,
    1,
    null,
    0
   ],
   [
    "tile_forbidden",
    1,
    1,
    null,
    0
   ],
   [
    "tile_forbidden",
    1,
    1,
    null,
    0
   ],
   [
    "tile_forbidden",
    1,
    1,
    null,
    0
   ],
   [
    "tile_forbidden",
    1,
    1,
    null,
    0
   ],
   [
    "tile_forbidden",
    1,
    1,
    null,
    0
   ],
   [
    "tile_forbidden",
    1,
    1,
    null,
    0
   ],
   [
    "tile_forbidden",
    1,
    1,
    null,
    0
   ],
   [
    "tile_forbidden",
    1,
    1,
    null,
    0
   ],
   [
    "tile_forbidden",
    1,
    1,
    null,
    0
   ],
   [
    "tile_forbidden",
    1,
    1,
    null,
    0
   ],
   [
    "tile_forbidden",
    1,
    1,
    null,
    0
   ],
   [
    "tile_forbidden",
    1,
    1,
    null,
    0
   ],
   [
    "tile_fence_bound",
    0,
    1,
    null,
    1
   ],
   [
    "tile_forbidden",
    1,
    1,
    null,
    0
   ],
   [
    "tile_fence_bound",
    0,
    1,
    null,
    1
   ],
   [
    "tile_fence_bound",
    0,
    1,
    null,
    1
   ],
   [
    "tile_forbidden",
    1,
    1,
    null,
    0
   ],
   [
    "tile_fence_bound",
    0,
    1,
    null,
    1
   ],
   [
    "tile_forbidden",
    1,
    1,
    null,
    0
   ],
   [
    "tile_forbidden",
    1,
    1,
    null,
    0
   ],
   [
    "tile_forbidden",
    1,
    1,
    null,
    0
   ],
   [
    "tile_forbidden",
    1,
    1,
    null,
    0
   ],
   [
    "tile_start",
    0,
    0,
    null,
    0
   ],
   [
    "tile_floor",
    0,
    0,
    null,
    0
   ],
   [
    "tile_floor",
    0,
    0,
    null,
    0
   ],
   [
    "tile_road",
    0,
    0,
    null,
    1
   ],
   [
    "tile_forbidden",
    1,
    1,
    null,
    0
   ],
   [
    "tile_forbidden",
    1,
    1,
    null,
    0
   ],
   [
    "tile_road",
    0,
    0,
    null,
    1
   ],
   [
    "tile_road",
    0,
    0,
    null,
    1
   ],
   [
    "tile_road",
    0,
    0,
    null,
    1
   ],
   [
    "tile_road",
    0,
    0,
    null,
    1
   ],
   [
    "tile_road",
    0,
    0,
    null,
    1
   ],
   [
    "tile_forbidden",
    1,
    1,
    null,
    0
   ],
   [
    "tile_start",
    0,
    0,
    null,
    0
   ],
   [
    "tile_floor",
    0,
    0,
    null,
    0
   ],
   [
    "tile_floor",
    0,
    0,
    null,
    0
   ],
   [
    "tile_road",
    0,
    0,
    null,
    1
   ],
   [
    "tile_wall",
    1,
    1,
    null,
    1
   ],
   [
    "tile_forbidden",
    1,
    1,
    null,
    0
   ],
   [
    "tile_road",
    0,
    0,
    null,
    1
   ],
   [
    "tile_forbidden",
    1,
    1,
    null,
    0
   ],
   [
    "tile_wall",
    1,
    1,
    null,
    1
   ],
   [
    "tile_wall",
    1,
    1,
    null,
    1
   ],
   [
    "tile_road",
    0,
    0,
    null,
    1
   ],
   [
    "tile_forbidden",
    1,
    1,
    null,
    0
   ],
   [
    "tile_forbidden",
    1,
    1,
    null,
    0
   ],
   [
    "tile_floor",
    0,
    0,
    null,
    0
   ],
   [
    "tile_flystart",
    1,
    1,
    null,
    0
   ],
   [
    "tile_road",
    0,
    0,
    null,
    1
   ],
   [
    "tile_wall",
    1,
    1,
    null,
    1
   ],
   [
    "tile_wall",
    1,
    1,
    null,
    1
   ],
   [
    "tile_road",
    0,
    0,
    null,
    1
   ],
   [
    "tile_forbidden",
    1,
    1,
    null,
    0
   ],
   [
    "tile_wall",
    1,
    1,
    null,
    1
   ],
   [
    "tile_forbidden",
    1,
    1,
    null,
    0
   ],
   [
    "tile_end",
    0,
    0,
    null,
    0
   ],
   [
    "tile_forbidden",
    1,
    1,
    null,
    0
   ],
   [
    "tile_forbidden",
    1,
    1,
    null,
    0
   ],
   [
    "tile_floor",
    0,
    0,
    null,
    0
   ],
   [
    "tile_forbidden",
    1,
    1,
    null,
    0
   ],
   [
    "tile_road",
    0,
    0,
    null,
    1
   ],
   [
    "tile_wall",
    1,
    1,
    null,
    1
   ],
   [
    "tile_wall",
    1,
    1,
    null,
    1
   ],
   [
    "tile_road",
    0,
    0,
    null,
    1
   ],
   [
    "tile_fence_bound",
    0,
    1,
    null,
    1
   ],
   [
    "tile_fence_bound",
    0,
    1,
    null,
    1
   ],
   [
    "tile_forbidden",
    1,
    1,
    null,
    0
   ],
   [
    "tile_forbidden",
    1,
    1,
    null,
    0
   ],
   [
    "tile_forbidden",
    1,
    1,
    null,
    0
   ],
   [
    "tile_forbidden",
    1,
    1,
    null,
    0
   ],
   [
    "tile_floor",
    0,
    0,
    null,
    0
   ],
   [
    "tile_forbidden",
    1,
    1,
    null,
    0
   ],
   [
    "tile_road",
    0,
    0,
    null,
    1
   ],
   [
    "tile_road",
    0,
    0,
    null,
    1
   ],
   [
    "tile_road",
    0,
    0,
    null,
    1
   ],
   [
    "tile_road",
    0,
    0,
    null,
    1
   ],
   [
    "tile_forbidden",
    1,
    1,
    null,
    0
   ],
   [
    "tile_forbidden",
    1,
    1,
    null,
    0
   ],
   [
    "tile_forbidden",
    1,
    1,
    null,
    0
   ],
   [
    "tile_forbidden",
    1,
    1,
    null,
    0
   ],
   [
    "tile_forbidden",
    1,
    1,
    null,
    0
   ],
   [
    "tile_forbidden",
    1,
    1,
    null,
    0
   ],
   [
    "tile_start",
    0,
    0,
    null,
    0
   ],
   [
    "tile_forbidden",
    1,
    1,
    null,
    0
   ],
   [
    "tile_forbidden",
    1,
    1,
    null,
    0
   ],
   [
    "tile_forbidden",
    1,
    1,
    null,
    0
   ],
   [
    "tile_forbidden",
    1,
    1,
    null,
    0
   ],
   [
    "tile_forbidden",
    1,
    1,
    null,
    0
   ],
   [
    "tile_forbidden",
    1,
    1,
    null,
    0
   ],
   [
    "tile_forbidden",
    1,
    1,
    null,
    0
   ],
   [
    "tile_forbidden",
    1,
    1,
    null,
    0
   ],
   [
    "tile_forbidden",
    1,
    1,
    null,
    0
   ],
   [
    "tile_forbidden",
    1,
    1,
    null,
    0
   ]
  ]
 },
 "extra_routes": [],
 "branches": null,
 "NORMAL": {
  "groupKey": null,
  "max_permutations": 1,
  "permutations": [
   {}
  ]
 },
 "ELITE": {
  "groupKey": null,
  "max_permutations": 1,
  "permutations": [
   {}
  ]
 },
 "waves": [
  {
   "preDelay": 0.0,
   "postDelay": 0.0,
   "maxTimeWaitingForNextWave": -1.0,
   "fragments": [
    {
     "preDelay": 0.0,
     "actions": [
      {
       "actionType": "SPAWN",
       "key": "enemy_1355_mrfly_2",
       "count": 1,
       "preDelay": 5.0,
       "interval": 1.0,
       "routeIndex": 0,
       "autoPreviewRoute": true,
       "hiddenGroup": null,
       "randomSpawnGroupKey": null,
       "randomSpawnGroupPackKey": null,
       "weight": 0,
       "dontBlockWave": false
      },
      {
       "actionType": "SPAWN",
       "key": "enemy_1353_esabr_2",
       "count": 2,
       "preDelay": 3.0,
       "interval": 3.0,
       "routeIndex": 1,
       "autoPreviewRoute": true,
       "hiddenGroup": null,
       "randomSpawnGroupKey": null,
       "randomSpawnGroupPackKey": null,
       "weight": 0,
       "dontBlockWave": false
      },
      {
       "actionType": "SPAWN",
       "key": "enemy_1353_esabr_2",
       "count": 3,
       "preDelay": 18.0,
       "interval": 4.0,
       "routeIndex": 1,
       "autoPreviewRoute": false,
       "hiddenGroup": null,
       "randomSpawnGroupKey": null,
       "randomSpawnGroupPackKey": null,
       "weight": 0,
       "dontBlockWave": false
      },
      {
       "actionType": "SPAWN",
       "key": "enemy_1354_eghost_2",
       "count": 1,
       "preDelay": 44.0,
       "interval": 1.0,
       "routeIndex": 2,
       "autoPreviewRoute": false,
       "hiddenGroup": null,
       "randomSpawnGroupKey": null,
       "randomSpawnGroupPackKey": null,
       "weight": 0,
       "dontBlockWave": false
      },
      {
       "actionType": "SPAWN",
       "key": "enemy_1354_eghost_2",
       "count": 1,
       "preDelay": 42.0,
       "interval": 1.0,
       "routeIndex": 3,
       "autoPreviewRoute": false,
       "hiddenGroup": null,
       "randomSpawnGroupKey": null,
       "randomSpawnGroupPackKey": null,
       "weight": 0,
       "dontBlockWave": false
      },
      {
       "actionType": "SPAWN",
       "key": "enemy_1354_eghost_2",
       "count": 1,
       "preDelay": 40.0,
       "interval": 1.0,
       "routeIndex": 4,
       "autoPreviewRoute": true,
       "hiddenGroup": null,
       "randomSpawnGroupKey": null,
       "randomSpawnGroupPackKey": null,
       "weight": 0,
       "dontBlockWave": false
      },
      {
       "actionType": "SPAWN",
       "key": "enemy_1358_esheld_2",
       "count": 1,
       "preDelay": 60.0,
       "interval": 1.0,
       "routeIndex": 5,
       "autoPreviewRoute": false,
       "hiddenGroup": null,
       "randomSpawnGroupKey": null,
       "randomSpawnGroupPackKey": null,
       "weight": 0,
       "dontBlockWave": false
      },
      {
       "actionType": "SPAWN",
       "key": "enemy_1358_esheld_2",
       "count": 1,
       "preDelay": 60.0,
       "interval": 1.0,
       "routeIndex": 6,
       "autoPreviewRoute": false,
       "hiddenGroup": null,
       "randomSpawnGroupKey": null,
       "randomSpawnGroupPackKey": null,
       "weight": 0,
       "dontBlockWave": false
      },
      {
       "actionType": "SPAWN",
       "key": "enemy_1358_esheld_2",
       "count": 1,
       "preDelay": 63.0,
       "interval": 1.0,
       "routeIndex": 7,
       "autoPreviewRoute": false,
       "hiddenGroup": null,
       "randomSpawnGroupKey": null,
       "randomSpawnGroupPackKey": null,
       "weight": 0,
       "dontBlockWave": false
      },
      {
       "actionType": "SPAWN",
       "key": "enemy_1358_esheld_2",
       "count": 1,
       "preDelay": 63.0,
       "interval": 1.0,
       "routeIndex": 8,
       "autoPreviewRoute": false,
       "hiddenGroup": null,
       "randomSpawnGroupKey": null,
       "randomSpawnGroupPackKey": null,
       "weight": 0,
       "dontBlockWave": false
      },
      {
       "actionType": "SPAWN",
       "key": "enemy_1353_esabr_2",
       "count": 4,
       "preDelay": 84.0,
       "interval": 6.0,
       "routeIndex": 1,
       "autoPreviewRoute": true,
       "hiddenGroup": null,
       "randomSpawnGroupKey": null,
       "randomSpawnGroupPackKey": null,
       "weight": 0,
       "dontBlockWave": false
      },
      {
       "actionType": "SPAWN",
       "key": "enemy_1356_egun_2",
       "count": 1,
       "preDelay": 120.0,
       "interval": 1.0,
       "routeIndex": 9,
       "autoPreviewRoute": false,
       "hiddenGroup": null,
       "randomSpawnGroupKey": null,
       "randomSpawnGroupPackKey": null,
       "weight": 0,
       "dontBlockWave": false
      },
      {
       "actionType": "SPAWN",
       "key": "enemy_1358_esheld_2",
       "count": 1,
       "preDelay": 122.0,
       "interval": 1.0,
       "routeIndex": 10,
       "autoPreviewRoute": false,
       "hiddenGroup": null,
       "randomSpawnGroupKey": null,
       "randomSpawnGroupPackKey": null,
       "weight": 0,
       "dontBlockWave": false
      },
      {
       "actionType": "SPAWN",
       "key": "enemy_1358_esheld_2",
       "count": 1,
       "preDelay": 119.0,
       "interval": 1.0,
       "routeIndex": 11,
       "autoPreviewRoute": false,
       "hiddenGroup": null,
       "randomSpawnGroupKey": null,
       "randomSpawnGroupPackKey": null,
       "weight": 0,
       "dontBlockWave": false
      },
      {
       "actionType": "SPAWN",
       "key": "enemy_1358_esheld_2",
       "count": 1,
       "preDelay": 122.0,
       "interval": 1.0,
       "routeIndex": 12,
       "autoPreviewRoute": false,
       "hiddenGroup": null,
       "randomSpawnGroupKey": null,
       "randomSpawnGroupPackKey": null,
       "weight": 0,
       "dontBlockWave": false
      },
      {
       "actionType": "SPAWN",
       "key": "enemy_1354_eghost_2",
       "count": 1,
       "preDelay": 130.0,
       "interval": 1.0,
       "routeIndex": 13,
       "autoPreviewRoute": false,
       "hiddenGroup": null,
       "randomSpawnGroupKey": null,
       "randomSpawnGroupPackKey": null,
       "weight": 0,
       "dontBlockWave": false
      },
      {
       "actionType": "SPAWN",
       "key": "enemy_1354_eghost_2",
       "count": 1,
       "preDelay": 133.0,
       "interval": 1.0,
       "routeIndex": 14,
       "autoPreviewRoute": false,
       "hiddenGroup": null,
       "randomSpawnGroupKey": null,
       "randomSpawnGroupPackKey": null,
       "weight": 0,
       "dontBlockWave": false
      },
      {
       "actionType": "SPAWN",
       "key": "enemy_1354_eghost_2",
       "count": 1,
       "preDelay": 136.0,
       "interval": 1.0,
       "routeIndex": 15,
       "autoPreviewRoute": false,
       "hiddenGroup": null,
       "randomSpawnGroupKey": null,
       "randomSpawnGroupPackKey": null,
       "weight": 0,
       "dontBlockWave": false
      },
      {
       "actionType": "SPAWN",
       "key": "enemy_1355_mrfly_2",
       "count": 1,
       "preDelay": 140.0,
       "interval": 1.0,
       "routeIndex": 16,
       "autoPreviewRoute": true,
       "hiddenGroup": null,
       "randomSpawnGroupKey": null,
       "randomSpawnGroupPackKey": null,
       "weight": 0,
       "dontBlockWave": false
      }
     ]
    }
   ],
   "advancedWaveTag": null
  }
 ],
 "bonus": {
  "type": "wave",
  "wave_index": -1,
  "frag_index": -1
 }
}